manhattan_mcp/__init__.py
manhattan_mcp/cli.py
manhattan_mcp/client.py
manhattan_mcp/config.py
manhattan_mcp/server.py
manhattan_mcp-0.1.9.dist-info/METADATA
manhattan_mcp-0.1.9.dist-info/WHEEL
manhattan_mcp-0.1.9.dist-info/entry_points.txt
manhattan_mcp-0.1.9.dist-info/licenses/LICENSE
manhattan_mcp-0.1.9.dist-info/RECORD
