Metadata-Version: 2.4
Name: manhattan-mcp
Version: 0.1.9
Summary: MCP Server for Manhattan Memory System - Give AI agents persistent memory
Project-URL: Homepage, https://themanhattanproject.ai
Project-URL: Documentation, https://themanhattanproject.ai/mcp-docs
Project-URL: Repository, https://github.com/agent-architects/manhattan-mcp
Author: Agent Architects Studio
License-Expression: MIT
License-File: LICENSE
Keywords: agent,ai,claude,llm,manhattan,mcp,memory
Classifier: Development Status :: 4 - Beta
Classifier: Intended Audience :: Developers
Classifier: License :: OSI Approved :: MIT License
Classifier: Programming Language :: Python :: 3
Classifier: Programming Language :: Python :: 3.10
Classifier: Programming Language :: Python :: 3.11
Classifier: Programming Language :: Python :: 3.12
Classifier: Topic :: Software Development :: Libraries :: Python Modules
Requires-Python: >=3.10
Requires-Dist: httpx>=0.25.0
Requires-Dist: mcp>=1.0.0
Requires-Dist: python-dotenv>=1.0.0
Provides-Extra: dev
Requires-Dist: pytest-asyncio>=0.21.0; extra == 'dev'
Requires-Dist: pytest>=7.0.0; extra == 'dev'
